cmem_plugin_ssh/__init__.py
cmem_plugin_ssh/autocompletion.py
cmem_plugin_ssh/download.py
cmem_plugin_ssh/execute_commands.py
cmem_plugin_ssh/list.py
cmem_plugin_ssh/retrieval.py
cmem_plugin_ssh/ssh-icon.svg
cmem_plugin_ssh/upload.py
cmem_plugin_ssh/utils.py
cmem_plugin_ssh-1.1.1.dist-info/METADATA
cmem_plugin_ssh-1.1.1.dist-info/WHEEL
cmem_plugin_ssh-1.1.1.dist-info/licenses/LICENSE
cmem_plugin_ssh-1.1.1.dist-info/RECORD
