Metadata-Version: 2.4
Name: cmem-plugin-ssh
Version: 1.1.1
Summary: Get files and process output via secure shell protocol.
License: Apache-2.0
License-File: LICENSE
Keywords: eccenca Corporate Memory,plugin
Author: eccenca GmbH
Author-email: cmempy-developer@eccenca.com
Requires-Python: >=3.13,<4.0
Classifier: Development Status :: 4 - Beta
Classifier: Environment :: Plugins
Classifier: License :: OSI Approved :: Apache Software License
Classifier: Programming Language :: Python :: 3
Classifier: Programming Language :: Python :: 3.13
Classifier: Programming Language :: Python :: 3.14
Requires-Dist: cmem-plugin-base (>=4.12.1,<5.0.0)
Requires-Dist: paramiko (>=3.5.1,<4.0.0)
Project-URL: Homepage, https://github.com/eccenca/cmem-plugin-ssh
